{
    "deployments": [
        {
            "quantity": 1,
            "pods": 10,
            "fanIn": 1,
            "fanOut": 100
        },
        {
            "quantity": 2,
            "pods": 10,
            "fanIn": 30,
            "fanOut": 30
        },
        {
            "quantity": 2,
            "pods": 10,
            "fanIn": 10,
            "fanOut": 10
        },
        {
            "quantity": 2,
            "pods": 10,
            "fanIn": 30,
            "fanOut": 0
        }
    ]
}
